db2az/__init__.py
db2az/cli.py
db2az/utils.py
db2azure_cli-1.0.5.dist-info/LICENSE
db2azure_cli-1.0.5.dist-info/METADATA
db2azure_cli-1.0.5.dist-info/WHEEL
db2azure_cli-1.0.5.dist-info/entry_points.txt
db2azure_cli-1.0.5.dist-info/top_level.txt
db2azure_cli-1.0.5.dist-info/RECORD
