Metadata-Version: 2.2
Name: db2azure_cli
Version: 1.0.5
Summary: A CLI tool to upload database query results to Azure storage.
Home-page: https://github.com/mr-speedster/DB2Azure-CLI
Author: Ajith D
Author-email: ajithd78564@gmail.com
Classifier: Programming Language :: Python :: 3
Classifier: License :: OSI Approved :: MIT License
Classifier: Operating System :: OS Independent
Requires-Python: >=3.7
License-File: LICENSE
Requires-Dist: typer[all]
Requires-Dist: inquirer
Requires-Dist: yaspin
Requires-Dist: pyfiglet
Requires-Dist: tabulate
Dynamic: author
Dynamic: author-email
Dynamic: classifier
Dynamic: description
Dynamic: description-content-type
Dynamic: home-page
Dynamic: requires-dist
Dynamic: requires-python
Dynamic: summary
